{
  "year": "2025-26",
  "nodes": [
    {
      "id": "income-tax",
      "name": "Income Tax",
      "group": "revenue",
      "value": 930198
    },
    {
      "id": "corporate-tax",
      "name": "Corporate Tax",
      "group": "revenue",
      "value": 699954
    },
    {
      "id": "gst",
      "name": "GST",
      "group": "revenue",
      "value": 762100
    },
    {
      "id": "excise",
      "name": "Excise Duty",
      "group": "revenue",
      "value": 205157
    },
    {
      "id": "customs",
      "name": "Customs Duty",
      "group": "revenue",
      "value": 240000
    },
    {
      "id": "non-tax-revenue",
      "name": "Non-Tax & Other Revenue",
      "group": "revenue",
      "value": 659000
    },
    {
      "id": "borrowings",
      "name": "Borrowings & Other Liabilities",
      "group": "revenue",
      "value": 1568936
    },
    {
      "id": "central-govt",
      "name": "Central Government",
      "group": "center",
      "value": 6482936
    },
    {
      "id": "states-tax-share",
      "name": "States' Share of Taxes",
      "group": "expenditure",
      "value": 1417591
    },
    {
      "id": "interest-payments",
      "name": "Interest Payments",
      "group": "expenditure",
      "value": 1080000
    },
    {
      "id": "defence",
      "name": "Defence",
      "group": "expenditure",
      "value": 681210
    },
    {
      "id": "rural-development",
      "name": "Rural Development",
      "group": "expenditure",
      "value": 178482
    },
    {
      "id": "agriculture",
      "name": "Agriculture & Farmers Welfare",
      "group": "expenditure",
      "value": 135580
    },
    {
      "id": "education",
      "name": "Education",
      "group": "expenditure",
      "value": 125638
    },
    {
      "id": "health",
      "name": "Health & Family Welfare",
      "group": "expenditure",
      "value": 90959
    },
    {
      "id": "railways",
      "name": "Railways",
      "group": "expenditure",
      "value": 265200
    },
    {
      "id": "home-affairs",
      "name": "Home Affairs",
      "group": "expenditure",
      "value": 221049
    },
    {
      "id": "road-transport",
      "name": "Road Transport & Highways",
      "group": "expenditure",
      "value": 278000
    },
    {
      "id": "transfers-to-states",
      "name": "Transfers to States & UTs",
      "group": "expenditure",
      "value": 1200000
    },
    {
      "id": "subsidies",
      "name": "Subsidies",
      "group": "expenditure",
      "value": 396000
    },
    {
      "id": "other-expenditure",
      "name": "Other",
      "group": "expenditure",
      "value": 413227
    }
  ],
  "links": [
    {
      "source": "income-tax",
      "target": "central-govt",
      "value": 930198,
      "verified": true
    },
    {
      "source": "corporate-tax",
      "target": "central-govt",
      "value": 699954,
      "verified": true
    },
    {
      "source": "gst",
      "target": "central-govt",
      "value": 762100,
      "verified": true
    },
    {
      "source": "excise",
      "target": "central-govt",
      "value": 205157,
      "verified": true
    },
    {
      "source": "customs",
      "target": "central-govt",
      "value": 240000,
      "verified": true
    },
    {
      "source": "non-tax-revenue",
      "target": "central-govt",
      "value": 659000,
      "verified": true
    },
    {
      "source": "borrowings",
      "target": "central-govt",
      "value": 1568936,
      "verified": true
    },
    {
      "source": "central-govt",
      "target": "states-tax-share",
      "value": 1417591,
      "verified": true
    },
    {
      "source": "central-govt",
      "target": "interest-payments",
      "value": 1080000,
      "verified": true
    },
    {
      "source": "central-govt",
      "target": "defence",
      "value": 681210,
      "verified": true
    },
    {
      "source": "central-govt",
      "target": "rural-development",
      "value": 178482,
      "verified": true
    },
    {
      "source": "central-govt",
      "target": "agriculture",
      "value": 135580,
      "verified": true
    },
    {
      "source": "central-govt",
      "target": "education",
      "value": 125638,
      "verified": true
    },
    {
      "source": "central-govt",
      "target": "health",
      "value": 90959,
      "verified": true
    },
    {
      "source": "central-govt",
      "target": "railways",
      "value": 265200,
      "verified": true
    },
    {
      "source": "central-govt",
      "target": "home-affairs",
      "value": 221049,
      "verified": true
    },
    {
      "source": "central-govt",
      "target": "road-transport",
      "value": 278000,
      "verified": true
    },
    {
      "source": "central-govt",
      "target": "transfers-to-states",
      "value": 1200000,
      "verified": true
    },
    {
      "source": "central-govt",
      "target": "subsidies",
      "value": 396000,
      "verified": true
    },
    {
      "source": "central-govt",
      "target": "other-expenditure",
      "value": 413227,
      "verified": true
    }
  ]
}